purehle/__init__.py
purehle/__main__.py
purehle/_cli.py
purehle/_common.py
purehle/_util.py
purehle/algorithms/__init__.py
purehle/algorithms/_md5.py
purehle/algorithms/_sha1.py
purehle/algorithms/_sha2.py
purehle/tests/__init__.py
purehle/tests/test_md5.py
purehle/tests/test_sha1.py
purehle/tests/test_sha2.py
purehle-1.0.1.dist-info/LICENSE
purehle-1.0.1.dist-info/METADATA
purehle-1.0.1.dist-info/WHEEL
purehle-1.0.1.dist-info/entry_points.txt
purehle-1.0.1.dist-info/top_level.txt
purehle-1.0.1.dist-info/RECORD
